{
    "bos @ tor": {
        "wind": "27% (Roof)",
        "time": "7:07PM",
        "stadium": "Rogers Centre",
        "conditions": "Breezy and Mostly Clear",
        "temp": "60",
        "feels like": "49",
        "precip %": "0%",
        "wind speed": "17.0 mph",
        "wind dir": "WNW",
        "transform": "transform: rotate(-217.500deg);"
    },
    "min @ cle": {
        "wind": "17.0 mph",
        "time": "6:10PM",
        "stadium": "Progressive Field",
        "conditions": "Light Rain and Breezy",
        "temp": "70",
        "feels like": "64",
        "precip %": "34%",
        "wind speed": "15.2 mph",
        "wind dir": "WNW",
        "transform": "transform: rotate(100.000deg);"
    },
    "kc @ tb": {
        "wind": "10%",
        "time": "7:05PM",
        "stadium": "George M. Steinbrenner Field",
        "conditions": "Partly Cloudy",
        "temp": "81",
        "feels like": "83",
        "precip %": "5%",
        "wind speed": "7.2 mph",
        "wind dir": "ENE",
        "transform": "transform: rotate(-210.000deg);"
    },
    "atl @ col": {
        "wind": "10.7 mph",
        "time": "8:40PM",
        "stadium": "Coors Field",
        "conditions": "Possible Light Rain",
        "temp": "58",
        "feels like": "49",
        "precip %": "20%",
        "wind speed": "9.8 mph",
        "wind dir": "SSW",
        "transform": "transform: rotate(14.375deg);"
    },
    "nyy @ bal": {
        "wind": "12.5 mph",
        "time": "6:35PM",
        "stadium": "Oriole Park at Camden Yards",
        "conditions": "Mostly Clear",
        "temp": "83",
        "feels like": "77",
        "precip %": "0%",
        "wind speed": "11.6 mph",
        "wind dir": "SSW",
        "transform": "transform: rotate(-2.500deg);"
    },
    "wsh @ phi": {
        "wind": "13.4 mph",
        "time": "6:45PM",
        "stadium": "Citizens Bank Park",
        "conditions": "Partly Cloudy",
        "temp": "78",
        "feels like": "72",
        "precip %": "0%",
        "wind speed": "12.5 mph",
        "wind dir": "SSW",
        "transform": "transform: rotate(13.125deg);"
    },
    "ari @ nym": {
        "wind": "16.1 mph",
        "time": "7:10PM",
        "stadium": "Citi Field",
        "conditions": "Breezy and Partly Cloudy",
        "temp": "70",
        "feels like": "62",
        "precip %": "0%",
        "wind speed": "15.2 mph",
        "wind dir": "SSW",
        "transform": "transform: rotate(3.125deg);"
    },
    "mil @ chw": {
        "wind": "0%",
        "time": "7:40PM",
        "stadium": "Rate Field",
        "conditions": "Mostly Clear",
        "temp": "55",
        "feels like": "48",
        "precip %": "0%",
        "wind speed": "8.0 mph",
        "wind dir": "NNE",
        "transform": "transform: rotate(-275.000deg);"
    },
    "ath @ tex": {
        "wind": "0% (Roof)",
        "time": "8:05PM",
        "stadium": "Globe Life Field",
        "conditions": "Partly Cloudy",
        "temp": "81",
        "feels like": "79",
        "precip %": "7%",
        "wind speed": "12.5 mph",
        "wind dir": "SSE",
        "transform": "transform: rotate(-85.000deg);"
    },
    "det @ hou": {
        "wind": "0% (Roof)",
        "time": "8:10PM",
        "stadium": "Daikin Park",
        "conditions": "Partly Cloudy",
        "temp": "79",
        "feels like": "79",
        "precip %": "0%",
        "wind speed": "12.5 mph",
        "wind dir": "SSE",
        "transform": "transform: rotate(-367.500deg);"
    },
    "laa @ sea": {
        "wind": "TBA% (Roof)",
        "time": "9:40PM",
        "stadium": "T-Mobile Park",
        "conditions": "Mostly Cloudy",
        "temp": "55",
        "feels like": "52",
        "precip %": "0%",
        "wind speed": "4.5 mph",
        "wind dir": "NNE",
        "transform": "transform: rotate(-195.000deg);"
    },
    "sf @ sd": {
        "wind": "TBA%",
        "time": "9:40PM",
        "stadium": "Petco Park",
        "conditions": "Mostly Clear",
        "temp": "61",
        "feels like": "61",
        "precip %": "0%",
        "wind speed": "3.6 mph",
        "wind dir": "WSW",
        "transform": "transform: rotate(90.000deg);"
    },
    "mia @ lad": {
        "wind": "0%",
        "time": "10:10PM",
        "stadium": "Dodger Stadium",
        "conditions": "Clear",
        "temp": "61",
        "feels like": "60",
        "precip %": "0%",
        "wind speed": "4.5 mph",
        "wind dir": "SSW",
        "transform": "transform: rotate(17.500deg);"
    },
    "stl @ cin": {
        "wind": "11.6 mph",
        "time": "6:40PM",
        "stadium": "Great American Ball Park",
        "conditions": "Light Rain",
        "temp": "74",
        "feels like": "74",
        "precip %": "48%",
        "wind speed": "9.8 mph",
        "wind dir": "WSW",
        "transform": "transform: rotate(-63.750deg);"
    },
    "chc @ pit": {
        "wind": "15.2 mph",
        "time": "6:40PM",
        "stadium": "PNC Park",
        "conditions": "Light Rain",
        "temp": "75",
        "feels like": "72",
        "precip %": "27%",
        "wind speed": "14.3 mph",
        "wind dir": "WSW",
        "transform": "transform: rotate(-62.500deg);"
    }
}