{
    "phi @ cle": {
        "kyle schwarber": {
            "cz": "260"
        },
        "bryce harper": {
            "cz": "320"
        },
        "jose ramirez": {
            "cz": "360"
        },
        "max kepler": {
            "cz": "380"
        },
        "nick castellanos": {
            "cz": "400"
        },
        "jhonkensy noel": {
            "cz": "400"
        },
        "carlos santana": {
            "cz": "450"
        },
        "jt realmuto": {
            "cz": "450"
        },
        "trea turner": {
            "cz": "480"
        },
        "brandon marsh": {
            "cz": "500"
        },
        "kyle manzardo": {
            "cz": "500"
        },
        "gabriel arias": {
            "cz": "550"
        },
        "alec bohm": {
            "cz": "600"
        },
        "angel martinez": {
            "cz": "650"
        },
        "bryson stott": {
            "cz": "650"
        },
        "austin hedges": {
            "cz": "700"
        },
        "steven kwan": {
            "cz": "800"
        },
        "daniel schneemann": {
            "cz": "1200"
        }
    },
    "stl @ wsh": {
        "willson contreras": {
            "cz": "380"
        },
        "lars nootbaar": {
            "cz": "400"
        },
        "jordan walker": {
            "cz": "450"
        },
        "cj abrams": {
            "cz": "500"
        },
        "nolan arenado": {
            "cz": "500"
        },
        "masyn winn": {
            "cz": "550"
        },
        "brendan donovan": {
            "cz": "550"
        },
        "alec burleson": {
            "cz": "550"
        },
        "yohel pozo": {
            "cz": "550"
        },
        "james wood": {
            "cz": "550"
        },
        "nathaniel lowe": {
            "cz": "600"
        },
        "josh bell": {
            "cz": "600"
        },
        "victor scott": {
            "cz": "600"
        },
        "keibert ruiz": {
            "cz": "650"
        },
        "dylan crews": {
            "cz": "650"
        },
        "luis garcia": {
            "cz": "750"
        },
        "jacob young": {
            "cz": "1000"
        },
        "amed rosario": {
            "cz": "1100"
        }
    },
    "mil @ tb": {
        "jonathan aranda": {
            "cz": "300"
        },
        "junior caminero": {
            "cz": "300"
        },
        "rhys hoskins": {
            "cz": "333"
        },
        "brandon lowe": {
            "cz": "340"
        },
        "jackson chourio": {
            "cz": "360"
        },
        "yandy diaz": {
            "cz": "380"
        },
        "william contreras": {
            "cz": "400"
        },
        "christian yelich": {
            "cz": "400"
        },
        "kameron misner": {
            "cz": "450"
        },
        "jake bauers": {
            "cz": "500"
        },
        "caleb durbin": {
            "cz": "550"
        },
        "taylor walls": {
            "cz": "650"
        },
        "ben rortvedt": {
            "cz": "700"
        },
        "joey ortiz": {
            "cz": "700"
        },
        "chandler simpson": {
            "cz": "700"
        },
        "brice turang": {
            "cz": "750"
        },
        "travis jankowski": {
            "cz": "800"
        },
        "sal frelick": {
            "cz": "800"
        }
    },
    "bos @ kc": {
        "salvador perez": {
            "cz": "450"
        },
        "bobby witt": {
            "cz": "500"
        },
        "alex bregman": {
            "cz": "500"
        },
        "kristian campbell": {
            "cz": "550"
        },
        "trevor story": {
            "cz": "550"
        },
        "hunter renfroe": {
            "cz": "550"
        },
        "rob refsnyder": {
            "cz": "650"
        },
        "ceddanne rafaela": {
            "cz": "650"
        },
        "vinnie pasquantino": {
            "cz": "700"
        },
        "maikel garcia": {
            "cz": "700"
        },
        "rafael devers": {
            "cz": "750"
        },
        "drew waters": {
            "cz": "750"
        },
        "jarren duran": {
            "cz": "900"
        },
        "mark canha": {
            "cz": "1100"
        },
        "carlos narvaez": {
            "cz": "1200"
        },
        "jonathan india": {
            "cz": "1200"
        }
    },
    "atl @ pit": {
        "oneil cruz": {
            "cz": "230"
        },
        "andrew mccutchen": {
            "cz": "360"
        },
        "joey bart": {
            "cz": "400"
        },
        "bryan reynolds": {
            "cz": "450"
        },
        "alexander canario": {
            "cz": "500"
        },
        "tommy pham": {
            "cz": "500"
        },
        "jared triolo": {
            "cz": "550"
        },
        "adam frazier": {
            "cz": "750"
        },
        "kebryan hayes": {
            "cz": "850"
        }
    },
    "chc @ nym": {
        "pete alonso": {
            "cz": "230"
        },
        "juan soto": {
            "cz": "275"
        },
        "francisco lindor": {
            "cz": "333"
        },
        "brandon nimmo": {
            "cz": "350"
        },
        "kyle tucker": {
            "cz": "360"
        },
        "mark vientos": {
            "cz": "360"
        },
        "michael busch": {
            "cz": "380"
        },
        "seiya suzuki": {
            "cz": "380"
        },
        "francisco alvarez": {
            "cz": "400"
        },
        "ian happ": {
            "cz": "400"
        },
        "pete crow armstrong": {
            "cz": "450"
        },
        "carson kelly": {
            "cz": "450"
        },
        "dansby swanson": {
            "cz": "450"
        },
        "tyrone taylor": {
            "cz": "500"
        },
        "starling marte": {
            "cz": "550"
        },
        "jon berti": {
            "cz": "750"
        },
        "nico hoerner": {
            "cz": "750"
        }
    },
    "cin @ hou": {
        "christian walker": {
            "cz": "360"
        },
        "jeremy pena": {
            "cz": "500"
        },
        "zach dezenzo": {
            "cz": "550"
        },
        "jose altuve": {
            "cz": "550"
        },
        "yainer diaz": {
            "cz": "550"
        },
        "brendan rodgers": {
            "cz": "600"
        },
        "jake meyers": {
            "cz": "650"
        },
        "isaac paredes": {
            "cz": "750"
        }
    }
}