{
    "nyy @ cle": {
        "aaron judge": {
            "dk": "+265"
        },
        "jazz chisholm": {
            "dk": "+450"
        },
        "kyle manzardo": {
            "dk": "+450"
        },
        "jose ramirez": {
            "dk": "+475"
        },
        "ben rice": {
            "dk": "+500"
        },
        "jasson dominguez": {
            "dk": "+550"
        },
        "austin wells": {
            "dk": "+600"
        },
        "carlos santana": {
            "dk": "+600"
        },
        "cody bellinger": {
            "dk": "+600"
        },
        "paul goldschmidt": {
            "dk": "+600"
        },
        "bo naylor": {
            "dk": "+650"
        },
        "anthony volpe": {
            "dk": "+950"
        },
        "nolan jones": {
            "dk": "+950"
        },
        "angel martinez": {
            "dk": "+1000"
        },
        "daniel schneemann": {
            "dk": "+1000"
        },
        "jorbit vivas": {
            "dk": "+1300"
        },
        "brayan rocchio": {
            "dk": "+1400"
        },
        "steven kwan": {
            "dk": "+1400"
        }
    },
    "sd @ det": {
        "fernando tatis": {
            "dk": "+280"
        },
        "manny machado": {
            "dk": "+450"
        },
        "spencer torkelson": {
            "dk": "+500"
        },
        "dillon dingler": {
            "dk": "+650"
        },
        "gleyber torres": {
            "dk": "+700"
        },
        "riley greene": {
            "dk": "+700"
        },
        "xander bogaerts": {
            "dk": "+850"
        },
        "javier baez": {
            "dk": "+900"
        },
        "tirso ornelas": {
            "dk": "+900"
        },
        "trey sweeney": {
            "dk": "+900"
        },
        "gavin sheets": {
            "dk": "+950"
        },
        "elias diaz": {
            "dk": "+1000"
        },
        "jace jung": {
            "dk": "+1000"
        },
        "colt keith": {
            "dk": "+1100"
        },
        "oscar gonzalez": {
            "dk": "+1100"
        },
        "jose iglesias": {
            "dk": "+1600"
        },
        "tyler wade": {
            "dk": "+2500"
        }
    },
    "cin @ mia": {
        "jesus sanchez": {
            "dk": "+450"
        },
        "matt mervis": {
            "dk": "+550"
        },
        "austin hays": {
            "dk": "+600"
        },
        "connor norby": {
            "dk": "+600"
        },
        "kyle stowers": {
            "dk": "+600"
        },
        "elly de la cruz": {
            "dk": "+650"
        },
        "matt mclain": {
            "dk": "+650"
        },
        "eric wagaman": {
            "dk": "+800"
        },
        "agustin ramirez": {
            "dk": "+850"
        },
        "spencer steer": {
            "dk": "+850"
        },
        "noelvi marte": {
            "dk": "+900"
        },
        "dane myers": {
            "dk": "+1100"
        },
        "jake fraley": {
            "dk": "+1100"
        },
        "otto lopez": {
            "dk": "+1100"
        },
        "tj friedl": {
            "dk": "+1100"
        },
        "gavin lux": {
            "dk": "+1200"
        },
        "jose trevino": {
            "dk": "+1400"
        },
        "xavier edwards": {
            "dk": "+1900"
        }
    },
    "bal @ wsh": {
        "tyler oneill": {
            "dk": "+270"
        },
        "gary sanchez": {
            "dk": "+370"
        },
        "james wood": {
            "dk": "+475"
        },
        "jordan westburg": {
            "dk": "+500"
        },
        "ryan mountcastle": {
            "dk": "+550"
        },
        "gunnar henderson": {
            "dk": "+600"
        },
        "josh bell": {
            "dk": "+600"
        },
        "keibert ruiz": {
            "dk": "+600"
        },
        "ramon laureano": {
            "dk": "+600"
        },
        "cedric mullins": {
            "dk": "+650"
        },
        "jose tena": {
            "dk": "+650"
        },
        "adley rutschman": {
            "dk": "+700"
        },
        "nathaniel lowe": {
            "dk": "+700"
        },
        "dylan crews": {
            "dk": "+750"
        },
        "luis garcia": {
            "dk": "+750"
        },
        "jorge mateo": {
            "dk": "+850"
        },
        "jacob young": {
            "dk": "+2000"
        },
        "nasim nunez": {
            "dk": "+2200"
        }
    },
    "sea @ bos": {
        "rafael devers": {
            "dk": "+285"
        },
        "wilyer abreu": {
            "dk": "+310"
        },
        "cal raleigh": {
            "dk": "+330"
        },
        "alex bregman": {
            "dk": "+425"
        },
        "jarren duran": {
            "dk": "+425"
        },
        "julio rodriguez": {
            "dk": "+500"
        },
        "jorge polanco": {
            "dk": "+550"
        },
        "randy arozarena": {
            "dk": "+550"
        },
        "trevor story": {
            "dk": "+550"
        },
        "triston casas": {
            "dk": "+550"
        },
        "luke raley": {
            "dk": "+600"
        },
        "ceddanne rafaela": {
            "dk": "+650"
        },
        "dylan moore": {
            "dk": "+650"
        },
        "kristian campbell": {
            "dk": "+650"
        },
        "carlos narvaez": {
            "dk": "+850"
        },
        "rowdy tellez": {
            "dk": "+900"
        },
        "jp crawford": {
            "dk": "+1300"
        },
        "ben williamson": {
            "dk": "+1600"
        }
    },
    "phi @ nym": {
        "kyle schwarber": {
            "dk": "+310"
        },
        "bryce harper": {
            "dk": "+360"
        },
        "mark vientos": {
            "dk": "+425"
        },
        "pete alonso": {
            "dk": "+425"
        },
        "francisco lindor": {
            "dk": "+450"
        },
        "max kepler": {
            "dk": "+500"
        },
        "juan soto": {
            "dk": "+550"
        },
        "nick castellanos": {
            "dk": "+550"
        },
        "trea turner": {
            "dk": "+550"
        },
        "jt realmuto": {
            "dk": "+600"
        },
        "tyrone taylor": {
            "dk": "+650"
        },
        "alec bohm": {
            "dk": "+800"
        },
        "bryson stott": {
            "dk": "+800"
        },
        "brandon nimmo": {
            "dk": "+900"
        },
        "luis torrens": {
            "dk": "+900"
        },
        "starling marte": {
            "dk": "+1100"
        },
        "luisangel acuna": {
            "dk": "+1200"
        },
        "johan rojas": {
            "dk": "+1500"
        }
    },
    "stl @ atl": {
        "marcell ozuna": {
            "dk": "+390"
        },
        "austin riley": {
            "dk": "+400"
        },
        "matt olson": {
            "dk": "+450"
        },
        "sean murphy": {
            "dk": "+550"
        },
        "jarred kelenic": {
            "dk": "+700"
        },
        "michael harris": {
            "dk": "+800"
        },
        "ozzie albies": {
            "dk": "+800"
        },
        "alex verdugo": {
            "dk": "+1100"
        },
        "nick allen": {
            "dk": "+2500"
        }
    },
    "col @ kc": {
        "salvador perez": {
            "dk": "+380"
        },
        "bobby witt": {
            "dk": "+400"
        },
        "brenton doyle": {
            "dk": "+500"
        },
        "hunter goodman": {
            "dk": "+500"
        },
        "michael toglia": {
            "dk": "+500"
        },
        "vinnie pasquantino": {
            "dk": "+500"
        },
        "jonathan india": {
            "dk": "+650"
        },
        "michael massey": {
            "dk": "+650"
        },
        "jordan beck": {
            "dk": "+700"
        },
        "sean bouchard": {
            "dk": "+700"
        },
        "kyle farmer": {
            "dk": "+750"
        },
        "drew waters": {
            "dk": "+800"
        },
        "jacob stallings": {
            "dk": "+800"
        },
        "freddy fermin": {
            "dk": "+850"
        },
        "ryan mcmahon": {
            "dk": "+950"
        },
        "maikel garcia": {
            "dk": "+1100"
        },
        "zac veen": {
            "dk": "+1300"
        },
        "kyle isbel": {
            "dk": "+1500"
        }
    },
    "chw @ min": {
        "byron buxton": {
            "dk": "+210"
        },
        "luis robert": {
            "dk": "+400"
        },
        "andrew vaughn": {
            "dk": "+475"
        },
        "ryan jeffers": {
            "dk": "+475"
        },
        "carlos correa": {
            "dk": "+500"
        },
        "harrison bader": {
            "dk": "+550"
        },
        "nick maton": {
            "dk": "+550"
        },
        "trevor larnach": {
            "dk": "+550"
        },
        "ty france": {
            "dk": "+550"
        },
        "andrew benintendi": {
            "dk": "+600"
        },
        "matt thaiss": {
            "dk": "+650"
        },
        "miguel vargas": {
            "dk": "+650"
        },
        "lenyn sosa": {
            "dk": "+700"
        },
        "brooks baldwin": {
            "dk": "+800"
        },
        "brooks lee": {
            "dk": "+850"
        },
        "edouard julien": {
            "dk": "+850"
        },
        "dashawn keirsey": {
            "dk": "+1000"
        },
        "jacob amaya": {
            "dk": "+1200"
        }
    },
    "lad @ chc": {
        "shohei ohtani": {
            "dk": "+265"
        },
        "teoscar hernandez": {
            "dk": "+275"
        },
        "will smith": {
            "dk": "+310"
        },
        "mookie betts": {
            "dk": "+350"
        },
        "max muncy": {
            "dk": "+380"
        },
        "andy pages": {
            "dk": "+390"
        },
        "tommy edman": {
            "dk": "+400"
        },
        "kyle tucker": {
            "dk": "+425"
        },
        "seiya suzuki": {
            "dk": "+450"
        },
        "freddie freeman": {
            "dk": "+500"
        },
        "ian happ": {
            "dk": "+500"
        },
        "michael busch": {
            "dk": "+500"
        },
        "dansby swanson": {
            "dk": "+550"
        },
        "carson kelly": {
            "dk": "+650"
        },
        "pete crow armstrong": {
            "dk": "+750"
        },
        "miguel rojas": {
            "dk": "+950"
        },
        "jon berti": {
            "dk": "+1500"
        },
        "nico hoerner": {
            "dk": "+1500"
        }
    },
    "tor @ hou": {
        "yordan alvarez": {
            "dk": "+280"
        },
        "anthony santander": {
            "dk": "+330"
        },
        "vladimir guerrero": {
            "dk": "+390"
        },
        "christian walker": {
            "dk": "+425"
        },
        "addison barger": {
            "dk": "+550"
        },
        "george springer": {
            "dk": "+550"
        },
        "bo bichette": {
            "dk": "+600"
        },
        "isaac paredes": {
            "dk": "+700"
        },
        "yainer diaz": {
            "dk": "+700"
        },
        "alan roden": {
            "dk": "+800"
        },
        "alejandro kirk": {
            "dk": "+800"
        },
        "jose altuve": {
            "dk": "+850"
        },
        "cam smith": {
            "dk": "+900"
        },
        "jeremy pena": {
            "dk": "+900"
        },
        "andres gimenez": {
            "dk": "+950"
        },
        "jake meyers": {
            "dk": "+1000"
        },
        "will wagner": {
            "dk": "+1000"
        },
        "mauricio dubon": {
            "dk": "+1900"
        }
    },
    "pit @ laa": {
        "jorge soler": {
            "dk": "+320"
        },
        "mike trout": {
            "dk": "+380"
        },
        "taylor ward": {
            "dk": "+450"
        },
        "logan ohoppe": {
            "dk": "+475"
        },
        "jo adell": {
            "dk": "+500"
        },
        "oneil cruz": {
            "dk": "+550"
        },
        "zach neto": {
            "dk": "+550"
        },
        "luis rengifo": {
            "dk": "+650"
        },
        "andrew mccutchen": {
            "dk": "+700"
        },
        "enmanuel valdez": {
            "dk": "+750"
        },
        "bryan reynolds": {
            "dk": "+800"
        },
        "joey bart": {
            "dk": "+850"
        },
        "kyren paris": {
            "dk": "+850"
        },
        "nolan schanuel": {
            "dk": "+1000"
        },
        "tommy pham": {
            "dk": "+1000"
        },
        "kebryan hayes": {
            "dk": "+1200"
        },
        "adam frazier": {
            "dk": "+1900"
        },
        "isiah kiner falefa": {
            "dk": "+2200"
        }
    },
    "tb @ ari": {
        "eugenio suarez": {
            "dk": "+285"
        },
        "corbin carroll": {
            "dk": "+290"
        },
        "pavin smith": {
            "dk": "+380"
        },
        "jonathan aranda": {
            "dk": "+450"
        },
        "brandon lowe": {
            "dk": "+475"
        },
        "josh naylor": {
            "dk": "+500"
        },
        "tim tawa": {
            "dk": "+500"
        },
        "danny jansen": {
            "dk": "+550"
        },
        "junior caminero": {
            "dk": "+550"
        },
        "lourdes gurriel": {
            "dk": "+550"
        },
        "kameron misner": {
            "dk": "+600"
        },
        "yandy diaz": {
            "dk": "+750"
        },
        "alek thomas": {
            "dk": "+800"
        },
        "geraldo perdomo": {
            "dk": "+850"
        },
        "gabriel moreno": {
            "dk": "+1100"
        },
        "taylor walls": {
            "dk": "+1100"
        },
        "chandler simpson": {
            "dk": "+1300"
        },
        "jake mangum": {
            "dk": "+1500"
        }
    },
    "mil @ sf": {
        "matt chapman": {
            "dk": "+370"
        },
        "willy adames": {
            "dk": "+500"
        },
        "heliot ramos": {
            "dk": "+550"
        },
        "rhys hoskins": {
            "dk": "+750"
        },
        "sam huff": {
            "dk": "+750"
        },
        "christian yelich": {
            "dk": "+800"
        },
        "david villar": {
            "dk": "+800"
        },
        "tyler fitzgerald": {
            "dk": "+800"
        },
        "wilmer flores": {
            "dk": "+850"
        },
        "jackson chourio": {
            "dk": "+900"
        },
        "luis matos": {
            "dk": "+950"
        },
        "william contreras": {
            "dk": "+1000"
        },
        "garrett mitchell": {
            "dk": "+1100"
        },
        "jung hoo lee": {
            "dk": "+1200"
        },
        "caleb durbin": {
            "dk": "+1800"
        },
        "joey ortiz": {
            "dk": "+1800"
        },
        "brice turang": {
            "dk": "+2000"
        },
        "sal frelick": {
            "dk": "+2500"
        }
    },
    "tex @ ath": {
        "brent rooker": {
            "dk": "+230"
        },
        "corey seager": {
            "dk": "+250"
        },
        "adolis garcia": {
            "dk": "+280"
        },
        "shea langeliers": {
            "dk": "+330"
        },
        "jake burger": {
            "dk": "+360"
        },
        "wyatt langford": {
            "dk": "+425"
        },
        "jj bleday": {
            "dk": "+475"
        },
        "josh smith": {
            "dk": "+500"
        },
        "lawrence butler": {
            "dk": "+500"
        },
        "marcus semien": {
            "dk": "+550"
        },
        "max muncy": {
            "dk": "+550"
        },
        "tyler soderstrom": {
            "dk": "+550"
        },
        "jonah heim": {
            "dk": "+600"
        },
        "josh jung": {
            "dk": "+650"
        },
        "dustin harris": {
            "dk": "+700"
        },
        "jacob wilson": {
            "dk": "+700"
        },
        "miguel andujar": {
            "dk": "+700"
        },
        "gio urshela": {
            "dk": "+900"
        }
    }
}