{
    "nyy @ ath": {
        "aaron judge": {
            "fd": "+164"
        },
        "ben rice": {
            "fd": "+280"
        },
        "brent rooker": {
            "fd": "+300"
        },
        "trent grisham": {
            "fd": "+300"
        },
        "shea langeliers": {
            "fd": "+390"
        },
        "tyler soderstrom": {
            "fd": "+400"
        },
        "lawrence butler": {
            "fd": "+420"
        },
        "jj bleday": {
            "fd": "+440"
        },
        "jasson dominguez": {
            "fd": "+470"
        },
        "paul goldschmidt": {
            "fd": "+480"
        },
        "luis urias": {
            "fd": "+600"
        },
        "jc escarra": {
            "fd": "+600"
        },
        "anthony volpe": {
            "fd": "+750"
        },
        "nick kurtz": {
            "fd": "+750"
        },
        "oswaldo cabrera": {
            "fd": "+750"
        },
        "miguel andujar": {
            "fd": "+900"
        },
        "jorbit vivas": {
            "fd": "+1100"
        },
        "jacob wilson": {
            "fd": "+1200"
        }
    }
}