{
    "min @ cle": {
        "": {
            "fd": "+1000"
        },
        "byron buxton": {
            "fd": "+1300"
        },
        "carlos santana": {
            "fd": "+1400"
        },
        "jhonkensy noel": {
            "fd": "+1400"
        },
        "brooks lee": {
            "fd": "+2000"
        },
        "trevor larnach": {
            "fd": "+2000"
        },
        "daniel schneemann": {
            "fd": "+2400"
        },
        "harrison bader": {
            "fd": "+2100"
        },
        "jonah bride": {
            "fd": "+3400"
        },
        "carlos correa": {
            "fd": "+2800"
        },
        "edouard julien": {
            "fd": "+3300"
        },
        "angel martinez": {
            "fd": "+3900"
        },
        "christian vazquez": {
            "fd": "+3900"
        }
    },
    "sf @ sd": {
        "matt chapman": {
            "fd": "+750"
        },
        "mike yastrzemski": {
            "fd": "+1200"
        },
        "": {
            "fd": "+1600"
        },
        "fernando tatis": {
            "fd": "+1100"
        },
        "wilmer flores": {
            "fd": "+1600"
        },
        "gavin sheets": {
            "fd": "+1700"
        },
        "jason heyward": {
            "fd": "+1800"
        },
        "jung hoo lee": {
            "fd": "+1900"
        },
        "xander bogaerts": {
            "fd": "+2500"
        },
        "manny machado": {
            "fd": "+2200"
        },
        "elias diaz": {
            "fd": "+2800"
        }
    },
    "laa @ sea": {
        "cal raleigh": {
            "fd": "+650"
        },
        "mike trout": {
            "fd": "+700"
        },
        "julio rodriguez": {
            "fd": "+900"
        },
        "jorge soler": {
            "fd": "+950"
        },
        "": {
            "fd": "+950"
        },
        "taylor ward": {
            "fd": "+1000"
        },
        "zach neto": {
            "fd": "+950"
        },
        "randy arozarena": {
            "fd": "+1200"
        },
        "logan ohoppe": {
            "fd": "+1200"
        },
        "rowdy tellez": {
            "fd": "+1400"
        },
        "kyren paris": {
            "fd": "+1600"
        },
        "nolan schanuel": {
            "fd": "+1800"
        },
        "luis rengifo": {
            "fd": "+2200"
        },
        "jp crawford": {
            "fd": "+2400"
        }
    },
    "mia @ lad": {
        "": {
            "fd": "+700"
        },
        "max muncy": {
            "fd": "+700"
        },
        "agustin ramirez": {
            "fd": "+750"
        },
        "andy pages": {
            "fd": "+700"
        },
        "connor norby": {
            "fd": "+800"
        },
        "jesus sanchez": {
            "fd": "+800"
        },
        "eric wagaman": {
            "fd": "+850"
        },
        "javier sanoja": {
            "fd": "+900"
        },
        "ronny simon": {
            "fd": "+1000"
        },
        "tommy edman": {
            "fd": "+1100"
        },
        "dane myers": {
            "fd": "+1300"
        },
        "otto lopez": {
            "fd": "+1700"
        },
        "xavier edwards": {
            "fd": "+2900"
        }
    }
}