{
    "stl @ atl": {
        "matt olson": {
            "fd": "+300"
        },
        "austin riley": {
            "fd": "+350"
        },
        "marcell ozuna": {
            "fd": "+350"
        },
        "nolan gorman": {
            "fd": "+400"
        },
        "michael harris": {
            "fd": "+440"
        },
        "willson contreras": {
            "fd": "+500"
        },
        "jarred kelenic": {
            "fd": "+520"
        },
        "lars nootbaar": {
            "fd": "+540"
        },
        "ozzie albies": {
            "fd": "+600"
        },
        "jordan walker": {
            "fd": "+680"
        },
        "alec burleson": {
            "fd": "+680"
        },
        "yohel pozo": {
            "fd": "+750"
        },
        "drake baldwin": {
            "fd": "+750"
        },
        "eli white": {
            "fd": "+800"
        },
        "nolan arenado": {
            "fd": "+830"
        },
        "victor scott": {
            "fd": "+830"
        },
        "masyn winn": {
            "fd": "+900"
        },
        "nick allen": {
            "fd": "+1700"
        }
    },
    "phi @ nym": {
        "pete alonso": {
            "fd": "+350"
        },
        "kyle schwarber": {
            "fd": "+420"
        },
        "juan soto": {
            "fd": "+420"
        },
        "francisco lindor": {
            "fd": "+450"
        },
        "mark vientos": {
            "fd": "+500"
        },
        "bryce harper": {
            "fd": "+540"
        },
        "brandon nimmo": {
            "fd": "+600"
        },
        "trea turner": {
            "fd": "+700"
        },
        "nick castellanos": {
            "fd": "+750"
        },
        "jt realmuto": {
            "fd": "+800"
        },
        "jesse winker": {
            "fd": "+830"
        },
        "weston wilson": {
            "fd": "+870"
        },
        "alec bohm": {
            "fd": "+900"
        },
        "tyrone taylor": {
            "fd": "+900"
        },
        "hayden senger": {
            "fd": "+900"
        },
        "brett baty": {
            "fd": "+900"
        },
        "edmundo sosa": {
            "fd": "+1000"
        },
        "johan rojas": {
            "fd": "+1500"
        }
    },
    "cin @ mia": {
        "matt mervis": {
            "fd": "+450"
        },
        "jesus sanchez": {
            "fd": "+520"
        },
        "jeimer candelario": {
            "fd": "+560"
        },
        "matt mclain": {
            "fd": "+560"
        },
        "kyle stowers": {
            "fd": "+600"
        },
        "elly de la cruz": {
            "fd": "+600"
        },
        "eric wagaman": {
            "fd": "+750"
        },
        "tj friedl": {
            "fd": "+830"
        },
        "noelvi marte": {
            "fd": "+870"
        },
        "gavin lux": {
            "fd": "+900"
        },
        "liam hicks": {
            "fd": "+900"
        },
        "spencer steer": {
            "fd": "+900"
        },
        "austin wynns": {
            "fd": "+1000"
        },
        "ronny simon": {
            "fd": "+1000"
        },
        "otto lopez": {
            "fd": "+1060"
        },
        "jake fraley": {
            "fd": "+1060"
        },
        "graham pauley": {
            "fd": "+1100"
        },
        "xavier edwards": {
            "fd": "+1100"
        }
    },
    "nyy @ cle": {
        "aaron judge": {
            "fd": "+255"
        },
        "ben rice": {
            "fd": "+350"
        },
        "jose ramirez": {
            "fd": "+400"
        },
        "jazz chisholm": {
            "fd": "+420"
        },
        "": {
            "fd": "+430"
        },
        "austin wells": {
            "fd": "+520"
        },
        "cody bellinger": {
            "fd": "+540"
        },
        "carlos santana": {
            "fd": "+560"
        },
        "jhonkensy noel": {
            "fd": "+560"
        },
        "jasson dominguez": {
            "fd": "+800"
        },
        "gabriel arias": {
            "fd": "+680"
        },
        "angel martinez": {
            "fd": "+830"
        },
        "austin hedges": {
            "fd": "+830"
        },
        "paul goldschmidt": {
            "fd": "+830"
        },
        "oswaldo cabrera": {
            "fd": "+900"
        },
        "steven kwan": {
            "fd": "+1000"
        },
        "brayan rocchio": {
            "fd": "+1060"
        },
        "anthony volpe": {
            "fd": "+1000"
        }
    },
    "sd @ det": {
        "spencer torkelson": {
            "fd": "+400"
        },
        "fernando tatis": {
            "fd": "+450"
        },
        "gleyber torres": {
            "fd": "+630"
        },
        "riley greene": {
            "fd": "+630"
        },
        "manny machado": {
            "fd": "+680"
        },
        "andy ibanez": {
            "fd": "+680"
        },
        "justyn henry malloy": {
            "fd": "+750"
        },
        "javier baez": {
            "fd": "+800"
        },
        "dillon dingler": {
            "fd": "+750"
        },
        "tirso ornelas": {
            "fd": "+800"
        },
        "zach mckinstry": {
            "fd": "+900"
        },
        "gavin sheets": {
            "fd": "+900"
        },
        "trey sweeney": {
            "fd": "+900"
        },
        "xander bogaerts": {
            "fd": "+1000"
        },
        "martin maldonado": {
            "fd": "+1060"
        },
        "oscar gonzalez": {
            "fd": "+1100"
        },
        "tyler wade": {
            "fd": "+1700"
        },
        "jose iglesias": {
            "fd": "+2500"
        }
    },
    "bal @ wsh": {
        "tyler oneill": {
            "fd": "+310"
        },
        "gunnar henderson": {
            "fd": "+390"
        },
        "james wood": {
            "fd": "+450"
        },
        "adley rutschman": {
            "fd": "+480"
        },
        "cedric mullins": {
            "fd": "+480"
        },
        "jordan westburg": {
            "fd": "+520"
        },
        "heston kjerstad": {
            "fd": "+520"
        },
        "keibert ruiz": {
            "fd": "+560"
        },
        "josh bell": {
            "fd": "+560"
        },
        "ryan mountcastle": {
            "fd": "+560"
        },
        "ryan ohearn": {
            "fd": "+600"
        },
        "luis garcia": {
            "fd": "+680"
        },
        "nathaniel lowe": {
            "fd": "+680"
        },
        "dylan crews": {
            "fd": "+700"
        },
        "jose tena": {
            "fd": "+750"
        },
        "jackson holliday": {
            "fd": "+830"
        },
        "nasim nunez": {
            "fd": "+1200"
        },
        "jacob young": {
            "fd": "+1400"
        }
    },
    "sea @ bos": {
        "cal raleigh": {
            "fd": "+320"
        },
        "rafael devers": {
            "fd": "+370"
        },
        "wilyer abreu": {
            "fd": "+390"
        },
        "alex bregman": {
            "fd": "+480"
        },
        "julio rodriguez": {
            "fd": "+520"
        },
        "jarren duran": {
            "fd": "+520"
        },
        "triston casas": {
            "fd": "+520"
        },
        "trevor story": {
            "fd": "+540"
        },
        "randy arozarena": {
            "fd": "+560"
        },
        "mitch garver": {
            "fd": "+600"
        },
        "dylan moore": {
            "fd": "+600"
        },
        "kristian campbell": {
            "fd": "+750"
        },
        "ben williamson": {
            "fd": "+800"
        },
        "luke raley": {
            "fd": "+800"
        },
        "carlos narvaez": {
            "fd": "+800"
        },
        "ceddanne rafaela": {
            "fd": "+830"
        },
        "donovan solano": {
            "fd": "+900"
        },
        "jp crawford": {
            "fd": "+1200"
        }
    },
    "lad @ chc": {
        "shohei ohtani": {
            "fd": "+340"
        },
        "teoscar hernandez": {
            "fd": "+360"
        },
        "kyle tucker": {
            "fd": "+370"
        },
        "seiya suzuki": {
            "fd": "+430"
        },
        "mookie betts": {
            "fd": "+450"
        },
        "will smith": {
            "fd": "+470"
        },
        "tommy edman": {
            "fd": "+470"
        },
        "max muncy": {
            "fd": "+470"
        },
        "michael busch": {
            "fd": "+480"
        },
        "ian happ": {
            "fd": "+500"
        },
        "dansby swanson": {
            "fd": "+520"
        },
        "enrique hernandez": {
            "fd": "+520"
        },
        "carson kelly": {
            "fd": "+540"
        },
        "andy pages": {
            "fd": "+540"
        },
        "freddie freeman": {
            "fd": "+680"
        },
        "pete crow armstrong": {
            "fd": "+680"
        },
        "jon berti": {
            "fd": "+1060"
        },
        "nico hoerner": {
            "fd": "+1060"
        }
    },
    "tor @ hou": {
        "yordan alvarez": {
            "fd": "+300"
        },
        "christian walker": {
            "fd": "+350"
        },
        "anthony santander": {
            "fd": "+350"
        },
        "vladimir guerrero": {
            "fd": "+450"
        },
        "jose altuve": {
            "fd": "+520"
        },
        "isaac paredes": {
            "fd": "+560"
        },
        "jeremy pena": {
            "fd": "+560"
        },
        "george springer": {
            "fd": "+600"
        },
        "bo bichette": {
            "fd": "+630"
        },
        "alan roden": {
            "fd": "+630"
        },
        "yainer diaz": {
            "fd": "+630"
        },
        "brendan rodgers": {
            "fd": "+630"
        },
        "jake meyers": {
            "fd": "+700"
        },
        "cam smith": {
            "fd": "+750"
        },
        "alejandro kirk": {
            "fd": "+750"
        },
        "andres gimenez": {
            "fd": "+800"
        },
        "ernie clement": {
            "fd": "+830"
        },
        "will wagner": {
            "fd": "+830"
        }
    },
    "col @ kc": {
        "bobby witt": {
            "fd": "+430"
        },
        "salvador perez": {
            "fd": "+470"
        },
        "hunter goodman": {
            "fd": "+600"
        },
        "mickey moniak": {
            "fd": "+600"
        },
        "michael toglia": {
            "fd": "+680"
        },
        "michael massey": {
            "fd": "+750"
        },
        "hunter renfroe": {
            "fd": "+800"
        },
        "vinnie pasquantino": {
            "fd": "+800"
        },
        "ryan mcmahon": {
            "fd": "+870"
        },
        "jonathan india": {
            "fd": "+870"
        },
        "aaron schunk": {
            "fd": "+870"
        },
        "kyle isbel": {
            "fd": "+900"
        },
        "adael amador": {
            "fd": "+900"
        },
        "drew waters": {
            "fd": "+900"
        },
        "zac veen": {
            "fd": "+1000"
        },
        "nick martini": {
            "fd": "+1060"
        },
        "kyle farmer": {
            "fd": "+1060"
        },
        "maikel garcia": {
            "fd": "+1200"
        }
    },
    "chw @ min": {
        "byron buxton": {
            "fd": "+330"
        },
        "luke keaschall": {
            "fd": "+470"
        },
        "ryan jeffers": {
            "fd": "+540"
        },
        "trevor larnach": {
            "fd": "+560"
        },
        "andrew vaughn": {
            "fd": "+600"
        },
        "luis robert": {
            "fd": "+600"
        },
        "andrew benintendi": {
            "fd": "+630"
        },
        "carlos correa": {
            "fd": "+630"
        },
        "edouard julien": {
            "fd": "+750"
        },
        "ty france": {
            "fd": "+750"
        },
        "harrison bader": {
            "fd": "+750"
        },
        "edgar quero": {
            "fd": "+750"
        },
        "nick maton": {
            "fd": "+800"
        },
        "brooks lee": {
            "fd": "+800"
        },
        "josh palacios": {
            "fd": "+800"
        },
        "miguel vargas": {
            "fd": "+870"
        },
        "lenyn sosa": {
            "fd": "+900"
        },
        "jacob amaya": {
            "fd": "+1200"
        }
    },
    "pit @ laa": {
        "mike trout": {
            "fd": "+260"
        },
        "jorge soler": {
            "fd": "+340"
        },
        "oneil cruz": {
            "fd": "+340"
        },
        "taylor ward": {
            "fd": "+450"
        },
        "jo adell": {
            "fd": "+480"
        },
        "logan ohoppe": {
            "fd": "+500"
        },
        "bryan reynolds": {
            "fd": "+520"
        },
        "andrew mccutchen": {
            "fd": "+560"
        },
        "zach neto": {
            "fd": "+560"
        },
        "enmanuel valdez": {
            "fd": "+630"
        },
        "luis rengifo": {
            "fd": "+630"
        },
        "joey bart": {
            "fd": "+680"
        },
        "kyren paris": {
            "fd": "+630"
        },
        "tommy pham": {
            "fd": "+900"
        },
        "kebryan hayes": {
            "fd": "+900"
        },
        "nolan schanuel": {
            "fd": "+1100"
        },
        "adam frazier": {
            "fd": "+1200"
        },
        "isiah kiner falefa": {
            "fd": "+1400"
        }
    },
    "tb @ ari": {
        "corbin carroll": {
            "fd": "+430"
        },
        "eugenio suarez": {
            "fd": "+450"
        },
        "josh naylor": {
            "fd": "+500"
        },
        "pavin smith": {
            "fd": "+540"
        },
        "junior caminero": {
            "fd": "+560"
        },
        "christopher morel": {
            "fd": "+560"
        },
        "lourdes gurriel": {
            "fd": "+600"
        },
        "yandy diaz": {
            "fd": "+630"
        },
        "danny jansen": {
            "fd": "+700"
        },
        "geraldo perdomo": {
            "fd": "+900"
        },
        "gabriel moreno": {
            "fd": "+900"
        },
        "alek thomas": {
            "fd": "+900"
        },
        "jose caballero": {
            "fd": "+1060"
        },
        "curtis mead": {
            "fd": "+1060"
        },
        "garrett hampson": {
            "fd": "+1200"
        },
        "chandler simpson": {
            "fd": "+1200"
        },
        "jake mangum": {
            "fd": "+1400"
        },
        "taylor walls": {
            "fd": "+1500"
        }
    },
    "mil @ sf": {
        "matt chapman": {
            "fd": "+520"
        },
        "willy adames": {
            "fd": "+630"
        },
        "heliot ramos": {
            "fd": "+680"
        },
        "mike yastrzemski": {
            "fd": "+700"
        },
        "sam huff": {
            "fd": "+800"
        },
        "rhys hoskins": {
            "fd": "+830"
        },
        "jung hoo lee": {
            "fd": "+900"
        },
        "wilmer flores": {
            "fd": "+900"
        },
        "tyler fitzgerald": {
            "fd": "+900"
        },
        "lamonte wade": {
            "fd": "+900"
        },
        "christian yelich": {
            "fd": "+1000"
        },
        "jackson chourio": {
            "fd": "+1060"
        },
        "william contreras": {
            "fd": "+1060"
        },
        "garrett mitchell": {
            "fd": "+1400"
        },
        "caleb durbin": {
            "fd": "+1500"
        },
        "brice turang": {
            "fd": "+1700"
        },
        "joey ortiz": {
            "fd": "+1700"
        },
        "sal frelick": {
            "fd": "+2500"
        }
    },
    "tex @ ath": {
        "brent rooker": {
            "fd": "+320"
        },
        "adolis garcia": {
            "fd": "+360"
        },
        "corey seager": {
            "fd": "+390"
        },
        "tyler soderstrom": {
            "fd": "+400"
        },
        "kyle higashioka": {
            "fd": "+400"
        },
        "jake burger": {
            "fd": "+400"
        },
        "wyatt langford": {
            "fd": "+400"
        },
        "shea langeliers": {
            "fd": "+420"
        },
        "lawrence butler": {
            "fd": "+440"
        },
        "josh jung": {
            "fd": "+500"
        },
        "marcus semien": {
            "fd": "+500"
        },
        "jj bleday": {
            "fd": "+540"
        },
        "jonah heim": {
            "fd": "+560"
        },
        "nick kurtz": {
            "fd": "+560"
        },
        "max p muncy": {
            "fd": "+800"
        },
        "leody taveras": {
            "fd": "+900"
        },
        "gio urshela": {
            "fd": "+1060"
        },
        "jacob wilson": {
            "fd": "+1100"
        }
    }
}