{
    "min @ cle": {
        "byron buxton": {
            "fd": "+700"
        },
        "jose ramirez": {
            "fd": "+850"
        },
        "kyle manzardo": {
            "fd": "+950"
        },
        "trevor larnach": {
            "fd": "+1100"
        },
        "jhonkensy noel": {
            "fd": "+1200"
        },
        "carlos santana": {
            "fd": "+1300"
        },
        "carlos correa": {
            "fd": "+1500"
        },
        "gabriel arias": {
            "fd": "+1400"
        },
        "brooks lee": {
            "fd": "+1900"
        },
        "daniel schneemann": {
            "fd": "+2000"
        },
        "": {
            "fd": "+2000"
        },
        "harrison bader": {
            "fd": "+2200"
        },
        "steven kwan": {
            "fd": "+2700"
        },
        "jonah bride": {
            "fd": "+3100"
        },
        "edouard julien": {
            "fd": "+3100"
        },
        "christian vazquez": {
            "fd": "+4100"
        }
    },
    "sf @ sd": {
        "matt chapman": {
            "fd": "+750"
        },
        "fernando tatis": {
            "fd": "+700"
        },
        "heliot ramos": {
            "fd": "+850"
        },
        "mike yastrzemski": {
            "fd": "+1100"
        },
        "tyler fitzgerald": {
            "fd": "+1300"
        },
        "lamonte wade": {
            "fd": "+1200"
        },
        "manny machado": {
            "fd": "+1300"
        },
        "patrick bailey": {
            "fd": "+1600"
        },
        "wilmer flores": {
            "fd": "+1600"
        },
        "": {
            "fd": "+1700"
        },
        "gavin sheets": {
            "fd": "+1700"
        },
        "jung hoo lee": {
            "fd": "+1900"
        },
        "xander bogaerts": {
            "fd": "+2200"
        }
    },
    "laa @ sea": {
        "cal raleigh": {
            "fd": "+550"
        },
        "julio rodriguez": {
            "fd": "+900"
        },
        "jo adell": {
            "fd": "+850"
        },
        "zach neto": {
            "fd": "+950"
        },
        "randy arozarena": {
            "fd": "+1100"
        },
        "leo rivas": {
            "fd": "+1100"
        },
        "rowdy tellez": {
            "fd": "+1300"
        },
        "kyren paris": {
            "fd": "+1300"
        },
        "luis rengifo": {
            "fd": "+1300"
        },
        "nolan schanuel": {
            "fd": "+1800"
        },
        "ben williamson": {
            "fd": "+2100"
        },
        "jp crawford": {
            "fd": "+2200"
        },
        "miles mastrobuoni": {
            "fd": "+4000"
        }
    },
    "mia @ lad": {
        "freddie freeman": {
            "fd": "+550"
        },
        "": {
            "fd": "+600"
        },
        "teoscar hernandez": {
            "fd": "+700"
        },
        "max muncy": {
            "fd": "+700"
        },
        "agustin ramirez": {
            "fd": "+700"
        },
        "ronny simon": {
            "fd": "+700"
        },
        "mookie betts": {
            "fd": "+700"
        },
        "andy pages": {
            "fd": "+750"
        },
        "will smith": {
            "fd": "+750"
        },
        "michael conforto": {
            "fd": "+900"
        },
        "eric wagaman": {
            "fd": "+900"
        },
        "connor norby": {
            "fd": "+800"
        },
        "javier sanoja": {
            "fd": "+850"
        },
        "tommy edman": {
            "fd": "+1200"
        },
        "dane myers": {
            "fd": "+1300"
        },
        "xavier edwards": {
            "fd": "+3200"
        }
    }
}